pydantic_chatcompletion/__init__.py
pydantic_chatcompletion-0.0.3.dist-info/METADATA
pydantic_chatcompletion-0.0.3.dist-info/WHEEL
pydantic_chatcompletion-0.0.3.dist-info/top_level.txt
pydantic_chatcompletion-0.0.3.dist-info/RECORD
